memotools/__init__.py
memotools/tag.py
memotools-0.0.1.dist-info/LICENSE
memotools-0.0.1.dist-info/METADATA
memotools-0.0.1.dist-info/WHEEL
memotools-0.0.1.dist-info/top_level.txt
memotools-0.0.1.dist-info/RECORD
